indico_migrate/__init__.py
indico_migrate/attachments.py
indico_migrate/badges_posters.py
indico_migrate/cli.py
indico_migrate/gui.py
indico_migrate/html.py
indico_migrate/importer.py
indico_migrate/logger.py
indico_migrate/migrate.py
indico_migrate/namespaces.py
indico_migrate/paste.py
indico_migrate/util.py
indico_migrate/version.py
indico_migrate/zodb_objects.py
indico_migrate/steps/__init__.py
indico_migrate/steps/badges_posters.py
indico_migrate/steps/categories.py
indico_migrate/steps/event_series.py
indico_migrate/steps/global_post_events.py
indico_migrate/steps/global_pre_events.py
indico_migrate/steps/room_bookings.py
indico_migrate/steps/rooms_locations.py
indico_migrate/steps/users_groups.py
indico_migrate/steps/events/__init__.py
indico_migrate/steps/events/abstracts.py
indico_migrate/steps/events/acls.py
indico_migrate/steps/events/importer.py
indico_migrate/steps/events/layout.py
indico_migrate/steps/events/logs.py
indico_migrate/steps/events/menus.py
indico_migrate/steps/events/misc.py
indico_migrate/steps/events/notes.py
indico_migrate/steps/events/papers.py
indico_migrate/steps/events/participants.py
indico_migrate/steps/events/registration.py
indico_migrate/steps/events/surveys.py
indico_migrate/steps/events/timetable.py
indico_migrate-1.0.10.dist-info/COPYING
indico_migrate-1.0.10.dist-info/METADATA
indico_migrate-1.0.10.dist-info/WHEEL
indico_migrate-1.0.10.dist-info/entry_points.txt
indico_migrate-1.0.10.dist-info/top_level.txt
indico_migrate-1.0.10.dist-info/RECORD
