Metadata-Version: 2.1
Name: indico-migrate
Version: 1.0.10
Summary: Migration from Indico 1.2 to 2.0
Home-page: https://github.com/indico/indico-migrate
Author: Indico Team
Author-email: indico-team@cern.ch
License: https://www.gnu.org/licenses/gpl-3.0.txt
Platform: UNKNOWN
Requires-Dist: indico (<2.1.dev0,>=2.0)
Requires-Dist: urwid (==1.3.1)
Requires-Dist: github3.py (==0.9.6)
Requires-Dist: ZODB3 (==3.10.5)
